interfaces/uart/vhdl_sources/uart_timing_gen.vhd
LIBRARY ieee;
USE ieee.std_logic_1164.ALL;
USE ieee.numeric_std.ALL;
USE ieee.math_real.ALL;

ENTITY uart_timing_gen IS
  GENERIC (
    g_clock_frequency : INTEGER := 100000000;
    g_baud_rate : INTEGER := 115200
  );
  PORT (
    clk : IN STD_LOGIC;
    ena : IN STD_LOGIC;

    bit_period2 : OUT STD_LOGIC;
    bit_period : OUT STD_LOGIC
  );
END ENTITY;

ARCHITECTURE behavior OF uart_timing_gen IS
  CONSTANT c_bit_period : INTEGER := g_clock_frequency / g_baud_rate;
  CONSTANT c_bit_period2 : INTEGER := g_clock_frequency / (2 * g_baud_rate);

  TYPE t_gen_state IS (Half, Full);
  SIGNAL state : t_gen_state;

  SIGNAL count : INTEGER := 0;
BEGIN

  p_timing_gen : PROCESS (clk)
  BEGIN
    IF rising_edge(clk) THEN
      bit_period <= '0';
      bit_period2 <= '0';
      IF ena = '1' THEN
        count <= count + 1;
        CASE state IS
          WHEN Half =>
            IF count = c_bit_period2 THEN
              bit_period2 <= '1';
              state <= Full;
              count <= 0;
            END IF;
          WHEN Full =>
            IF count = c_bit_period THEN
              bit_period <= '1';
              count <= 0;
            END IF;
        END CASE;
      ELSE
        state <= Half;
        count <= 0;
      END IF;
    END IF;
  END PROCESS;
END ARCHITECTURE;

components/input_sync/vhdl_sources/input_sync.vhd
LIBRARY ieee;
USE ieee.std_logic_1164.ALL;
USE ieee.numeric_std.ALL;
USE ieee.math_real.ALL;

ENTITY input_sync IS
  GENERIC (
    g_sync_stages : INTEGER RANGE 2 TO 16 := 2;
    g_reset_val : STD_LOGIC := '0'
  );
  PORT (
    input : IN STD_LOGIC;
    reset : IN STD_LOGIC;
    dest_clk : IN STD_LOGIC;
    output : OUT STD_LOGIC
  );
END ENTITY;

ARCHITECTURE behavior OF input_sync IS
  SIGNAL output_sr : STD_LOGIC_VECTOR(g_sync_stages - 1 DOWNTO 0) := (OTHERS => g_reset_val);

  ATTRIBUTE ASYNC_REG : STRING;
  ATTRIBUTE ASYNC_REG OF output_sr : SIGNAL IS "TRUE";
BEGIN
  output <= output_sr(output_sr'high);

  p_reg : PROCESS (dest_clk)
  BEGIN
    IF rising_edge(dest_clk) THEN
      output_sr <= output_sr(output_sr'high - 1 DOWNTO 0) & input;

      IF reset = '1' THEN
        output_sr <= (OTHERS => g_reset_val);
      END IF;
    END IF;
  END PROCESS;
END ARCHITECTURE;

interfaces/uart/vhdl_sources/uart_rx.vhd
LIBRARY ieee;
USE ieee.std_logic_1164.ALL;
USE ieee.numeric_std.ALL;
USE ieee.math_real.ALL;

ENTITY uart_rx IS
  GENERIC (
    g_clock_frequency : INTEGER := 100000000;
    g_baud_rate : INTEGER := 115200;
    g_data_bits : INTEGER := 8;
    g_stop_bits : INTEGER := 1
  );
  PORT (
    clk : IN STD_LOGIC;
    reset : IN STD_LOGIC;

    rx : IN STD_LOGIC;

    m_axis_tdata : OUT STD_LOGIC_VECTOR(g_data_bits - 1 DOWNTO 0);
    m_axis_tvalid : OUT STD_LOGIC;

    uart_error : OUT STD_LOGIC
  );
END ENTITY;

ARCHITECTURE structure OF uart_rx IS
  TYPE t_uart_state IS (Idle, Start, Data, Stop, Error);
  SIGNAL state : t_uart_state;

  SIGNAL timing_ena : STD_LOGIC;
  SIGNAL bit_period : STD_LOGIC;
  SIGNAL bit_period2 : STD_LOGIC;

  SIGNAL data_i : STD_LOGIC_VECTOR(g_data_bits - 1 DOWNTO 0);
  SIGNAL done_i : STD_LOGIC_VECTOR(g_data_bits - 1 DOWNTO 0);

  SIGNAL rx_sync : STD_LOGIC;
BEGIN
  input_sync_inst : ENTITY work.input_sync
    GENERIC MAP(
      g_sync_stages => 2,
      g_reset_val => '1'
    )
    PORT MAP(
      input => rx,
      reset => reset,
      dest_clk => clk,
      output => rx_sync
    );

  uart_timing_gen_inst : ENTITY work.uart_timing_gen
    GENERIC MAP(
      g_clock_frequency => g_clock_frequency,
      g_baud_rate => g_baud_rate
    )
    PORT MAP(
      clk => clk,
      ena => timing_ena,
      bit_period2 => bit_period2,
      bit_period => bit_period
    );

  p_state_machine : PROCESS (clk)
    VARIABLE v_count : INTEGER := 0;
  BEGIN
    IF rising_edge(clk) THEN
      uart_error <= '0';
      m_axis_tvalid <= '0';

      CASE state IS
        WHEN Idle =>
          IF rx_sync = '0' THEN
            timing_ena <= '1';
            state <= Start;
          END IF;
        WHEN Start =>
          IF bit_period2 = '1' THEN
            state <= Data;
            done_i <= (0 => '1', OTHERS => '0');
          END IF;
        WHEN Data =>
          IF bit_period = '1' THEN
            data_i <= rx_sync & data_i(g_data_bits - 1 DOWNTO 1);
            done_i <= done_i(g_data_bits - 2 DOWNTO 0) & done_i(g_data_bits - 1);

            IF done_i(g_data_bits - 1) = '1' THEN
              state <= Stop;
            END IF;
          END IF;

        WHEN Stop =>
          IF bit_period = '1' THEN
            timing_ena <= '0';
            IF rx_sync = '1' THEN
              m_axis_tvalid <= '1';
              m_axis_tdata <= data_i;
              timing_ena <= '0';
              state <= Idle;
            ELSE
              state <= Error;
            END IF;
          END IF;
        WHEN Error =>
          state <= Idle;
          uart_error <= '1';
      END CASE;

      IF reset = '1' THEN
        state <= Idle;
        data_i <= (OTHERS => '0');
        done_i <= (OTHERS => '0');
      END IF;
    END IF;
  END PROCESS;
END ARCHITECTURE;

interfaces/uart/build/waveform.vcd
$date
  Tue Mar 24 20:29:31 2026
$end
$version
  GHDL v0
$end
$timescale
  1 ps
$end
$scope module standard $end
$upscope $end
$scope module std_logic_1164 $end
$upscope $end
$scope module numeric_std $end
$upscope $end
$scope module math_real $end
$upscope $end
$scope module uart_rx $end
$var reg 1 ! clk $end
$var reg 1 " reset $end
$var reg 1 # rx $end
$var reg 8 $ m_axis_tdata[7:0] $end
$var reg 1 % m_axis_tvalid $end
$var reg 1 & uart_error $end
$comment state is not handled $end
$var reg 1 ' timing_ena $end
$var reg 1 ( bit_period $end
$var reg 1 ) bit_period2 $end
$var reg 8 * data_i[7:0] $end
$var reg 8 + done_i[7:0] $end
$var reg 1 , rx_sync $end
$scope module input_sync_inst $end
$var reg 1 - input $end
$var reg 1 . reset $end
$var reg 1 / dest_clk $end
$var reg 1 0 output $end
$var reg 2 1 output_sr[1:0] $end
$upscope $end
$scope module uart_timing_gen_inst $end
$var reg 1 2 clk $end
$var reg 1 3 ena $end
$var reg 1 4 bit_period2 $end
$var reg 1 5 bit_period $end
$comment state is not handled $end
$var integer 32 6 count $end
$upscope $end
$upscope $end
$enddefinitions $end
#0
1!
1"
U#
bUUUUUUUU $
U%
U&
U'
U(
U)
bUUUUUUUU *
bUUUUUUUU +
1,
U-
1.
1/
10
b11 1
12
U3
U4
U5
b0 6
#5000
0!
0/
02
#10000
1!
0%
0(
0)
b00000000 *
b00000000 +
1/
12
04
05
#15000
0!
0/
02
#20000
1!
1/
12
#25000
0!
0/
02
#30000
1!
1/
12
#35000
0!
0/
02
#40000
1!
1/
12
#45000
0!
0/
02
#50000
1!
1/
12
#55000
0!
0/
02
#60000
1!
1/
12
#65000
0!
0/
02
#70000
1!
1/
12
#75000
0!
0/
02
#80000
1!
1/
12
#85000
0!
0/
02
#90000
1!
1/
12
#95000
0!
0/
02
#100000
1!
1/
12
#105000
0!
0/
02
#110000
1!
1/
12
#115000
0!
0/
02
#120000
1!
1/
12
#125000
0!
0/
02
#130000
1!
1/
12
#135000
0!
0/
02
#140000
1!
1/
12
#145000
0!
0/
02
#150000
1!
1/
12
#155000
0!
0/
02
#160000
1!
1/
12
#165000
0!
0/
02
#170000
1!
1/
12
#175000
0!
0/
02
#180000
1!
1/
12
#185000
0!
0/
02
#190000
1!
1/
12
#195000
0!
0/
02
#200000
1!
1/
12
#205000
0!
0/
02
#210000
1!
1/
12
#215000
0!
0/
02
#220000
1!
1/
12
#225000
0!
0/
02
#230000
1!
1/
12
#235000
0!
0/
02
#240000
1!
1/
12
#245000
0!
0/
02
#250000
1!
1/
12
#255000
0!
0/
02
#260000
1!
1/
12
#265000
0!
0/
02
#270000
1!
1/
12
#275000
0!
0/
02
#280000
1!
1/
12
#285000
0!
0/
02
#290000
1!
1/
12
#295000
0!
0/
02
#300000
1!
1/
12
#305000
0!
0/
02
#310000
1!
1/
12
#315000
0!
0/
02
#320000
1!
1/
12
#325000
0!
0/
02
#330000
1!
1/
12
#335000
0!
0/
02
#340000
1!
1/
12
#345000
0!
0/
02
#350000
1!
1/
12
#355000
0!
0/
02
#360000
1!
1/
12
#365000
0!
0/
02
#370000
1!
1/
12
#375000
0!
0/
02
#380000
1!
1/
12
#385000
0!
0/
02
#390000
1!
1/
12
#395000
0!
0/
02
#400000
1!
1/
12
#405000
0!
0/
02
#410000
1!
1/
12
#415000
0!
0/
02
#420000
1!
1/
12
#425000
0!
0/
02
#430000
1!
1/
12
#435000
0!
0/
02
#440000
1!
1/
12
#445000
0!
0/
02
#450000
1!
1/
12
#455000
0!
0/
02
#460000
1!
1/
12
#465000
0!
0/
02
#470000
1!
1/
12
#475000
0!
0/
02
#480000
1!
1/
12
#485000
0!
0/
02
#490000
1!
1/
12
#495000
0!
0/
02
#500000
1!
1/
12
#505000
0!
0/
02
#510000
1!
1/
12
#515000
0!
0/
02
#520000
1!
1/
12
#525000
0!
0/
02
#530000
1!
1/
12
#535000
0!
0/
02
#540000
1!
1/
12
#545000
0!
0/
02
#550000
1!
1/
12
#555000
0!
0/
02
#560000
1!
1/
12
#565000
0!
0/
02
#570000
1!
1/
12
#575000
0!
0/
02
#580000
1!
1/
12
#585000
0!
0/
02
#590000
1!
1/
12
#595000
0!
0/
02
#600000
1!
1/
12
#605000
0!
0/
02
#610000
1!
1/
12
#615000
0!
0/
02
#620000
1!
1/
12
#625000
0!
0/
02
#630000
1!
1/
12
#635000
0!
0/
02
#640000
1!
1/
12
#645000
0!
0/
02
#650000
1!
1/
12
#655000
0!
0/
02
#660000
1!
1/
12
#665000
0!
0/
02
#670000
1!
1/
12
#675000
0!
0/
02
#680000
1!
1/
12
#685000
0!
0/
02
#690000
1!
1/
12
#695000
0!
0/
02
#700000
1!
1/
12
#705000
0!
0/
02
#710000
1!
1/
12
#715000
0!
0/
02
#720000
1!
1/
12
#725000
0!
0/
02
#730000
1!
1/
12
#735000
0!
0/
02
#740000
1!
1/
12
#745000
0!
0/
02
#750000
1!
1/
12
#755000
0!
0/
02
#760000
1!
1/
12
#765000
0!
0/
02
#770000
1!
1/
12
#775000
0!
0/
02
#780000
1!
1/
12
#785000
0!
0/
02
#790000
1!
1/
12
#795000
0!
0/
02
#800000
1!
1/
12
#805000
0!
0/
02
#810000
1!
1/
12
#815000
0!
0/
02
#820000
1!
1/
12
#825000
0!
0/
02
#830000
1!
1/
12
#835000
0!
0/
02
#840000
1!
1/
12
#845000
0!
0/
02
#850000
1!
1/
12
#855000
0!
0/
02
#860000
1!
1/
12
#865000
0!
0/
02
#870000
1!
1/
12
#875000
0!
0/
02
#880000
1!
1/
12
#885000
0!
0/
02
#890000
1!
1/
12
#895000
0!
0/
02
#900000
1!
1/
12
#905000
0!
0/
02
#910000
1!
1/
12
#915000
0!
0/
02
#920000
1!
1/
12
#925000
0!
0/
02
#930000
1!
1/
12
#935000
0!
0/
02
#940000
1!
1/
12
#945000
0!
0/
02
#950000
1!
1/
12
#955000
0!
0/
02
#960000
1!
1/
12
#965000
0!
0/
02
#970000
1!
1/
12
#975000
0!
0/
02
#980000
1!
1/
12
#985000
0!
0/
02
#990000
1!
0"
0#
0-
0.
1/
12
#995000
0!
0/
02
#1000000
1!
1/
b10 1
12
#1005000
0!
0/
02
#1010000
1!
0,
1/
00
b00 1
12
#1015000
0!
0/
02
#1020000
1!
1'
1/
12
13
#1025000
0!
0/
02
#1030000
1!
1/
12
b1 6
#1035000
0!
0/
02
#1040000
1!
1/
12
b10 6
#1045000
0!
0/
02
#1050000
1!
1/
12
b11 6
#1055000
0!
0/
02
#1060000
1!
1/
12
b100 6
#1065000
0!
0/
02
#1070000
1!
1/
12
b101 6
#1075000
0!
0/
02
#1080000
1!
1/
12
b110 6
#1085000
0!
0/
02
#1090000
1!
1/
12
b111 6
#1095000
0!
0/
02
#1100000
1!
1/
12
b1000 6
#1105000
0!
0/
02
#1110000
1!
1/
12
b1001 6
#1115000
0!
0/
02
#1120000
1!
1/
12
b1010 6
#1125000
0!
0/
02
#1130000
1!
1/
12
b1011 6
#1135000
0!
0/
02
#1140000
1!
1/
12
b1100 6
#1145000
0!
0/
02
#1150000
1!
1/
12
b1101 6
#1155000
0!
0/
02
#1160000
1!
1/
12
b1110 6
#1165000
0!
0/
02
#1170000
1!
1/
12
b1111 6
#1175000
0!
0/
02
#1180000
1!
1/
12
b10000 6
#1185000
0!
0/
02
#1190000
1!
1/
12
b10001 6
#1195000
0!
0/
02
#1200000
1!
1/
12
b10010 6
#1205000
0!
0/
02
#1210000
1!
1/
12
b10011 6
#1215000
0!
0/
02
#1220000
1!
1/
12
b10100 6
#1225000
0!
0/
02
#1230000
1!
1/
12
b10101 6
#1235000
0!
0/
02
#1240000
1!
1/
12
b10110 6
#1245000
0!
0/
02
#1250000
1!
1/
12
b10111 6
#1255000
0!
0/
02
#1260000
1!
1/
12
b11000 6
#1265000
0!
0/
02
#1270000
1!
1/
12
b11001 6
#1275000
0!
0/
02
#1280000
1!
1/
12
b11010 6
#1285000
0!
0/
02
#1290000
1!
1/
12
b11011 6
#1295000
0!
0/
02
#1300000
1!
1/
12
b11100 6
#1305000
0!
0/
02
#1310000
1!
1/
12
b11101 6
#1315000
0!
0/
02
#1320000
1!
1/
12
b11110 6
#1325000
0!
0/
02
#1330000
1!
1/
12
b11111 6
#1335000
0!
0/
02
#1340000
1!
1/
12
b100000 6
#1345000
0!
0/
02
#1350000
1!
1/
12
b100001 6
#1355000
0!
0/
02
#1360000
1!
1/
12
b100010 6
#1365000
0!
0/
02
#1370000
1!
1/
12
b100011 6
#1375000
0!
0/
02
#1380000
1!
1/
12
b100100 6
#1385000
0!
0/
02
#1390000
1!
1/
12
b100101 6
#1395000
0!
0/
02
#1400000
1!
1/
12
b100110 6
#1405000
0!
0/
02
#1410000
1!
1/
12
b100111 6
#1415000
0!
0/
02
#1420000
1!
1/
12
b101000 6
#1425000
0!
0/
02
#1430000
1!
1/
12
b101001 6
#1435000
0!
0/
02
#1440000
1!
1/
12
b101010 6
#1445000
0!
0/
02
#1450000
1!
1/
12
b101011 6
#1455000
0!
0/
02
#1460000
1!
1/
12
b101100 6
#1465000
0!
0/
02
#1470000
1!
1/
12
b101101 6
#1475000
0!
0/
02
#1480000
1!
1/
12
b101110 6
#1485000
0!
0/
02
#1490000
1!
1/
12
b101111 6
#1495000
0!
0/
02
#1500000
1!
1/
12
b110000 6
#1505000
0!
0/
02
#1510000
1!
1/
12
b110001 6
#1515000
0!
0/
02
#1520000
1!
1/
12
b110010 6
#1525000
0!
0/
02
#1530000
1!
1/
12
b110011 6
#1535000
0!
0/
02
#1540000
1!
1/
12
b110100 6
#1545000
0!
0/
02
#1550000
1!
1/
12
b110101 6
#1555000
0!
0/
02
#1560000
1!
1/
12
b110110 6
#1565000
0!
0/
02
#1570000
1!
1/
12
b110111 6
#1575000
0!
0/
02
#1580000
1!
1/
12
b111000 6
#1585000
0!
0/
02
#1590000
1!
1/
12
b111001 6
#1595000
0!
0/
02
#1600000
1!
1/
12
b111010 6
#1605000
0!
0/
02
#1610000
1!
1/
12
b111011 6
#1615000
0!
0/
02
#1620000
1!
1/
12
b111100 6
#1625000
0!
0/
02
#1630000
1!
1/
12
b111101 6
#1635000
0!
0/
02
#1640000
1!
1/
12
b111110 6
#1645000
0!
0/
02
#1650000
1!
1/
12
b111111 6
#1655000
0!
0/
02
#1660000
1!
1/
12
b1000000 6
#1665000
0!
0/
02
#1670000
1!
1/
12
b1000001 6
#1675000
0!
0/
02
#1680000
1!
1/
12
b1000010 6
#1685000
0!
0/
02
#1690000
1!
1/
12
b1000011 6
#1695000
0!
0/
02
#1700000
1!
1/
12
b1000100 6
#1705000
0!
0/
02
#1710000
1!
1/
12
b1000101 6
#1715000
0!
0/
02
#1720000
1!
1/
12
b1000110 6
#1725000
0!
0/
02
#1730000
1!
1/
12
b1000111 6
#1735000
0!
0/
02
#1740000
1!
1/
12
b1001000 6
#1745000
0!
0/
02
#1750000
1!
1/
12
b1001001 6
#1755000
0!
0/
02
#1760000
1!
1/
12
b1001010 6
#1765000
0!
0/
02
#1770000
1!
1/
12
b1001011 6
#1775000
0!
0/
02
#1780000
1!
1/
12
b1001100 6
#1785000
0!
0/
02
#1790000
1!
1/
12
b1001101 6
#1795000
0!
0/
02
#1800000
1!
1/
12
b1001110 6
#1805000
0!
0/
02
#1810000
1!
1/
12
b1001111 6
#1815000
0!
0/
02
#1820000
1!
1/
12
b1010000 6
#1825000
0!
0/
02
#1830000
1!
1/
12
b1010001 6
#1835000
0!
0/
02
#1840000
1!
1/
12
b1010010 6
#1845000
0!
0/
02
#1850000
1!
1/
12
b1010011 6
#1855000
0!
0/
02
#1860000
1!
1/
12
b1010100 6
#1865000
0!
0/
02
#1870000
1!
1/
12
b1010101 6
#1875000
0!
0/
02
#1880000
1!
1/
12
b1010110 6
#1885000
0!
0/
02
#1890000
1!
1/
12
b1010111 6
#1895000
0!
0/
02
#1900000
1!
1/
12
b1011000 6
#1905000
0!
0/
02
#1910000
1!
1/
12
b1011001 6
#1915000
0!
0/
02
#1920000
1!
1/
12
b1011010 6
#1925000
0!
0/
02
#1930000
1!
1/
12
b1011011 6
#1935000
0!
0/
02
#1940000
1!
1/
12
b1011100 6
#1945000
0!
0/
02
#1950000
1!
1/
12
b1011101 6
#1955000
0!
0/
02
#1960000
1!
1/
12
b1011110 6
#1965000
0!
0/
02
#1970000
1!
1/
12
b1011111 6
#1975000
0!
0/
02
#1980000
1!
1/
12
b1100000 6
#1985000
0!
0/
02
#1990000
1!
1/
12
b1100001 6
#1995000
0!
0/
02
#2000000
1!
1/
12
b1100010 6
#2005000
0!
0/
02
#2010000
1!
1/
12
b1100011 6
#2015000
0!
0/
02
#2020000
1!
1/
12
b1100100 6
#2025000
0!
0/
02
#2030000
1!
1/
12
b1100101 6
#2035000
0!
0/
02
#2040000
1!
1/
12
b1100110 6
#2045000
0!
0/
02
#2050000
1!
1/
12
b1100111 6
#2055000
0!
0/
02
#2060000
1!
1/
12
b1101000 6
#2065000
0!
0/
02
#2070000
1!
1/
12
b1101001 6
#2075000
0!
0/
02
#2080000
1!
1/
12
b1101010 6
#2085000
0!
0/
02
#2090000
1!
1/
12
b1101011 6
#2095000
0!
0/
02
#2100000
1!
1/
12
b1101100 6
#2105000
0!
0/
02
#2110000
1!
1/
12
b1101101 6
#2115000
0!
0/
02
#2120000
1!
1/
12
b1101110 6
#2125000
0!
0/
02
#2130000
1!
1/
12
b1101111 6
#2135000
0!
0/
02
#2140000
1!
1/
12
b1110000 6
#2145000
0!
0/
02
#2150000
1!
1/
12
b1110001 6
#2155000
0!
0/
02
#2160000
1!
1/
12
b1110010 6
#2165000
0!
0/
02
#2170000
1!
1/
12
b1110011 6
#2175000
0!
0/
02
#2180000
1!
1/
12
b1110100 6
#2185000
0!
0/
02
#2190000
1!
1/
12
b1110101 6
#2195000
0!
0/
02
#2200000
1!
1/
12
b1110110 6
#2205000
0!
0/
02
#2210000
1!
1/
12
b1110111 6
#2215000
0!
0/
02
#2220000
1!
1/
12
b1111000 6
#2225000
0!
0/
02
#2230000
1!
1/
12
b1111001 6
#2235000
0!
0/
02
#2240000
1!
1/
12
b1111010 6
#2245000
0!
0/
02
#2250000
1!
1/
12
b1111011 6
#2255000
0!
0/
02
#2260000
1!
1/
12
b1111100 6
#2265000
0!
0/
02
#2270000
1!
1/
12
b1111101 6
#2275000
0!
0/
02
#2280000
1!
1/
12
b1111110 6
#2285000
0!
0/
02
#2290000
1!
1/
12
b1111111 6
#2295000
0!
0/
02
#2300000
1!
1/
12
b10000000 6
#2305000
0!
0/
02
#2310000
1!
1/
12
b10000001 6
#2315000
0!
0/
02
#2320000
1!
1/
12
b10000010 6
#2325000
0!
0/
02
#2330000
1!
1/
12
b10000011 6
#2335000
0!
0/
02
#2340000
1!
1/
12
b10000100 6
#2345000
0!
0/
02
#2350000
1!
1/
12
b10000101 6
#2355000
0!
0/
02
#2360000
1!
1/
12
b10000110 6
#2365000
0!
0/
02
#2370000
1!
1/
12
b10000111 6
#2375000
0!
0/
02
#2380000
1!
1/
12
b10001000 6
#2385000
0!
0/
02
#2390000
1!
1/
12
b10001001 6
#2395000
0!
0/
02
#2400000
1!
1/
12
b10001010 6
#2405000
0!
0/
02
#2410000
1!
1/
12
b10001011 6
#2415000
0!
0/
02
#2420000
1!
1/
12
b10001100 6
#2425000
0!
0/
02
#2430000
1!
1/
12
b10001101 6
#2435000
0!
0/
02
#2440000
1!
1/
12
b10001110 6
#2445000
0!
0/
02
#2450000
1!
1/
12
b10001111 6
#2455000
0!
0/
02
#2460000
1!
1/
12
b10010000 6
#2465000
0!
0/
02
#2470000
1!
1/
12
b10010001 6
#2475000
0!
0/
02
#2480000
1!
1/
12
b10010010 6
#2485000
0!
0/
02
#2490000
1!
1/
12
b10010011 6
#2495000
0!
0/
02
#2500000
1!
1/
12
b10010100 6
#2505000
0!
0/
02
#2510000
1!
1/
12
b10010101 6
#2515000
0!
0/
02
#2520000
1!
1/
12
b10010110 6
#2525000
0!
0/
02
#2530000
1!
1/
12
b10010111 6
#2535000
0!
0/
02
#2540000
1!
1/
12
b10011000 6
#2545000
0!
0/
02
#2550000
1!
1/
12
b10011001 6
#2555000
0!
0/
02
#2560000
1!
1/
12
b10011010 6
#2565000
0!
0/
02
#2570000
1!
1/
12
b10011011 6
#2575000
0!
0/
02
#2580000
1!
1/
12
b10011100 6
#2585000
0!
0/
02
#2590000
1!
1/
12
b10011101 6
#2595000
0!
0/
02
#2600000
1!
1/
12
b10011110 6
#2605000
0!
0/
02
#2610000
1!
1/
12
b10011111 6
#2615000
0!
0/
02
#2620000
1!
1/
12
b10100000 6
#2625000
0!
0/
02
#2630000
1!
1/
12
b10100001 6
#2635000
0!
0/
02
#2640000
1!
1/
12
b10100010 6
#2645000
0!
0/
02
#2650000
1!
1/
12
b10100011 6
#2655000
0!
0/
02
#2660000
1!
1/
12
b10100100 6
#2665000
0!
0/
02
#2670000
1!
1/
12
b10100101 6
#2675000
0!
0/
02
#2680000
1!
1/
12
b10100110 6
#2685000
0!
0/
02
#2690000
1!
1/
12
b10100111 6
#2695000
0!
0/
02
#2700000
1!
1/
12
b10101000 6
#2705000
0!
0/
02
#2710000
1!
1/
12
b10101001 6
#2715000
0!
0/
02
#2720000
1!
1/
12
b10101010 6
#2725000
0!
0/
02
#2730000
1!
1/
12
b10101011 6
#2735000
0!
0/
02
#2740000
1!
1/
12
b10101100 6
#2745000
0!
0/
02
#2750000
1!
1/
12
b10101101 6
#2755000
0!
0/
02
#2760000
1!
1/
12
b10101110 6
#2765000
0!
0/
02
#2770000
1!
1/
12
b10101111 6
#2775000
0!
0/
02
#2780000
1!
1/
12
b10110000 6
#2785000
0!
0/
02
#2790000
1!
1/
12
b10110001 6
#2795000
0!
0/
02
#2800000
1!
1/
12
b10110010 6
#2805000
0!
0/
02
#2810000
1!
1/
12
b10110011 6
#2815000
0!
0/
02
#2820000
1!
1/
12
b10110100 6
#2825000
0!
0/
02
#2830000
1!
1/
12
b10110101 6
#2835000
0!
0/
02
#2840000
1!
1/
12
b10110110 6
#2845000
0!
0/
02
#2850000
1!
1/
12
b10110111 6
#2855000
0!
0/
02
#2860000
1!
1/
12
b10111000 6
#2865000
0!
0/
02
#2870000
1!
1/
12
b10111001 6
#2875000
0!
0/
02
#2880000
1!
1/
12
b10111010 6
#2885000
0!
0/
02
#2890000
1!
1/
12
b10111011 6
#2895000
0!
0/
02
#2900000
1!
1/
12
b10111100 6
#2905000
0!
0/
02
#2910000
1!
1/
12
b10111101 6
#2915000
0!
0/
02
#2920000
1!
1/
12
b10111110 6
#2925000
0!
0/
02
#2930000
1!
1/
12
b10111111 6
#2935000
0!
0/
02
#2940000
1!
1/
12
b11000000 6
#2945000
0!
0/
02
#2950000
1!
1/
12
b11000001 6
#2955000
0!
0/
02
#2960000
1!
1/
12
b11000010 6
#2965000
0!
0/
02
#2970000
1!
1/
12
b11000011 6
#2975000
0!
0/
02
#2980000
1!
1/
12
b11000100 6
#2985000
0!
0/
02
#2990000
1!
1/
12
b11000101 6
#2995000
0!
0/
02
#3000000
1!
1/
12
b11000110 6
#3005000
0!
0/
02
#3010000
1!
1/
12
b11000111 6
#3015000
0!
0/
02
#3020000
1!
1/
12
b11001000 6
#3025000
0!
0/
02
#3030000
1!
1/
12
b11001001 6
#3035000
0!
0/
02
#3040000
1!
1/
12
b11001010 6
#3045000
0!
0/
02
#3050000
1!
1/
12
b11001011 6
#3055000
0!
0/
02
#3060000
1!
1/
12
b11001100 6
#3065000
0!
0/
02
#3070000
1!
1/
12
b11001101 6
#3075000
0!
0/
02
#3080000
1!
1/
12
b11001110 6
#3085000
0!
0/
02
#3090000
1!
1/
12
b11001111 6
#3095000
0!
0/
02
#3100000
1!
1/
12
b11010000 6
#3105000
0!
0/
02
#3110000
1!
1/
12
b11010001 6
#3115000
0!
0/
02
#3120000
1!
1/
12
b11010010 6
#3125000
0!
0/
02
#3130000
1!
1/
12
b11010011 6
#3135000
0!
0/
02
#3140000
1!
1/
12
b11010100 6
#3145000
0!
0/
02
#3150000
1!
1/
12
b11010101 6
#3155000
0!
0/
02
#3160000
1!
1/
12
b11010110 6
#3165000
0!
0/
02
#3170000
1!
1/
12
b11010111 6
#3175000
0!
0/
02
#3180000
1!
1/
12
b11011000 6
#3185000
0!
0/
02
#3190000
1!
1/
12
b11011001 6
#3195000
0!
0/
02
#3200000
1!
1/
12
b11011010 6
#3205000
0!
0/
02
#3210000
1!
1/
12
b11011011 6
#3215000
0!
0/
02
#3220000
1!
1/
12
b11011100 6
#3225000
0!
0/
02
#3230000
1!
1/
12
b11011101 6
#3235000
0!
0/
02
#3240000
1!
1/
12
b11011110 6
#3245000
0!
0/
02
#3250000
1!
1/
12
b11011111 6
#3255000
0!
0/
02
#3260000
1!
1/
12
b11100000 6
#3265000
0!
0/
02
#3270000
1!
1/
12
b11100001 6
#3275000
0!
0/
02
#3280000
1!
1/
12
b11100010 6
#3285000
0!
0/
02
#3290000
1!
1/
12
b11100011 6
#3295000
0!
0/
02
#3300000
1!
1/
12
b11100100 6
#3305000
0!
0/
02
#3310000
1!
1/
12
b11100101 6
#3315000
0!
0/
02
#3320000
1!
1/
12
b11100110 6
#3325000
0!
0/
02
#3330000
1!
1/
12
b11100111 6
#3335000
0!
0/
02
#3340000
1!
1/
12
b11101000 6
#3345000
0!
0/
02
#3350000
1!
1/
12
b11101001 6
#3355000
0!
0/
02
#3360000
1!
1/
12
b11101010 6
#3365000
0!
0/
02
#3370000
1!
1/
12
b11101011 6
#3375000
0!
0/
02
#3380000
1!
1/
12
b11101100 6
#3385000
0!
0/
02
#3390000
1!
1/
12
b11101101 6
#3395000
0!
0/
02
#3400000
1!
1/
12
b11101110 6
#3405000
0!
0/
02
#3410000
1!
1/
12
b11101111 6
#3415000
0!
0/
02
#3420000
1!
1/
12
b11110000 6
#3425000
0!
0/
02
#3430000
1!
1/
12
b11110001 6
#3435000
0!
0/
02
#3440000
1!
1/
12
b11110010 6
#3445000
0!
0/
02
#3450000
1!
1/
12
b11110011 6
#3455000
0!
0/
02
#3460000
1!
1/
12
b11110100 6
#3465000
0!
0/
02
#3470000
1!
1/
12
b11110101 6
#3475000
0!
0/
02
#3480000
1!
1/
12
b11110110 6
#3485000
0!
0/
02
#3490000
1!
1/
12
b11110111 6
#3495000
0!
0/
02
#3500000
1!
1/
12
b11111000 6
#3505000
0!
0/
02
#3510000
1!
1/
12
b11111001 6
#3515000
0!
0/
02
#3520000
1!
1/
12
b11111010 6
#3525000
0!
0/
02
#3530000
1!
1/
12
b11111011 6
#3535000
0!
0/
02
#3540000
1!
1/
12
b11111100 6
#3545000
0!
0/
02
#3550000
1!
1/
12
b11111101 6
#3555000
0!
0/
02
#3560000
1!
1/
12
b11111110 6
#3565000
0!
0/
02
#3570000
1!
1/
12
b11111111 6
#3575000
0!
0/
02
#3580000
1!
1/
12
b100000000 6
#3585000
0!
0/
02
#3590000
1!
1/
12
b100000001 6
#3595000
0!
0/
02
#3600000
1!
1/
12
b100000010 6
#3605000
0!
0/
02
#3610000
1!
1/
12
b100000011 6
#3615000
0!
0/
02
#3620000
1!
1/
12
b100000100 6
#3625000
0!
0/
02
#3630000
1!
1/
12
b100000101 6
#3635000
0!
0/
02
#3640000
1!
1/
12
b100000110 6
#3645000
0!
0/
02
#3650000
1!
1/
12
b100000111 6
#3655000
0!
0/
02
#3660000
1!
1/
12
b100001000 6
#3665000
0!
0/
02
#3670000
1!
1/
12
b100001001 6
#3675000
0!
0/
02
#3680000
1!
1/
12
b100001010 6
#3685000
0!
0/
02
#3690000
1!
1/
12
b100001011 6
#3695000
0!
0/
02
#3700000
1!
1/
12
b100001100 6
#3705000
0!
0/
02
#3710000
1!
1/
12
b100001101 6
#3715000
0!
0/
02
#3720000
1!
1/
12
b100001110 6
#3725000
0!
0/
02
#3730000
1!
1/
12
b100001111 6
#3735000
0!
0/
02
#3740000
1!
1/
12
b100010000 6
#3745000
0!
0/
02
#3750000
1!
1/
12
b100010001 6
#3755000
0!
0/
02
#3760000
1!
1/
12
b100010010 6
#3765000
0!
0/
02
#3770000
1!
1/
12
b100010011 6
#3775000
0!
0/
02
#3780000
1!
1/
12
b100010100 6
#3785000
0!
0/
02
#3790000
1!
1/
12
b100010101 6
