components/input_sync/vhdl_sources/input_sync.vhd
LIBRARY ieee;
USE ieee.std_logic_1164.ALL;
USE ieee.numeric_std.ALL;
USE ieee.math_real.ALL;

ENTITY input_sync IS
  GENERIC (
    g_sync_stages : INTEGER RANGE 2 TO 16 := 2;
    g_reset_val : STD_LOGIC := '0'
  );
  PORT (
    input : IN STD_LOGIC;
    reset : IN STD_LOGIC;
    dest_clk : IN STD_LOGIC;
    output : OUT STD_LOGIC
  );
END ENTITY;

ARCHITECTURE behavior OF input_sync IS
  SIGNAL output_sr : STD_LOGIC_VECTOR(g_sync_stages - 1 DOWNTO 0) := (OTHERS => g_reset_val);

  ATTRIBUTE IOB : STRING;
  ATTRIBUTE IOB OF output_sr : SIGNAL IS "TRUE";
  ATTRIBUTE ASYNC_REG : STRING;
  ATTRIBUTE ASYNC_REG OF output_sr : SIGNAL IS "TRUE";
BEGIN
  output <= output_sr(output_sr'high);

  p_reg : PROCESS (dest_clk)
  BEGIN
    IF rising_edge(dest_clk) THEN
      output_sr <= output_sr(output_sr'high - 1 DOWNTO 0) & input;

      IF reset = '1' THEN
        output_sr <= (OTHERS => g_reset_val);
      END IF;
    END IF;
  END PROCESS;
END ARCHITECTURE;

interfaces/uart/vhdl_sources/uart_rx.vhd
LIBRARY ieee;
USE ieee.std_logic_1164.ALL;
USE ieee.numeric_std.ALL;
USE ieee.math_real.ALL;

ENTITY uart_rx IS
  GENERIC (
    g_clock_frequency : INTEGER := 100000000;
    g_baud_rate : INTEGER := 115200;
    g_data_bits : INTEGER := 8;
    g_stop_bits : INTEGER := 1
  );
  PORT (
    clk : IN STD_LOGIC;
    reset : IN STD_LOGIC;

    rx : IN STD_LOGIC;

    m_axis_tdata : OUT STD_LOGIC_VECTOR(g_data_bits - 1 DOWNTO 0);
    m_axis_tvalid : OUT STD_LOGIC;

    uart_error : OUT STD_LOGIC
  );
END ENTITY;

ARCHITECTURE structure OF uart_rx IS
  CONSTANT c_bit_period : INTEGER := g_clock_frequency / g_baud_rate;
  CONSTANT c_baud_tick_period : INTEGER := c_bit_period / 16;

  SIGNAL baud_tick : STD_LOGIC;
  SIGNAL sample : STD_LOGIC;
  SIGNAL sample_count : INTEGER RANGE 0 TO 15;

  TYPE t_uart_state IS (Idle, Start, Data, Stop, Error);
  SIGNAL state : t_uart_state;

  SIGNAL rx_sync : STD_LOGIC;
  SIGNAL rx_sr : STD_LOGIC_VECTOR(2 DOWNTO 0);
  SIGNAL rx_filter : STD_LOGIC;

  SIGNAL data_i : STD_LOGIC_VECTOR(m_axis_tdata'RANGE);
  SIGNAL bit_index : STD_LOGIC_VECTOR(m_axis_tdata'RANGE);
BEGIN
  input_sync_inst : ENTITY work.input_sync
    GENERIC MAP(
      g_sync_stages => 2,
      g_reset_val => '1'
    )
    PORT MAP(
      input => rx,
      reset => reset,
      dest_clk => clk,
      output => rx_sync
    );

  p_oversampling : PROCESS (clk)
    VARIABLE v_count : INTEGER := 0;
  BEGIN
    IF rising_edge(clk) THEN
      baud_tick <= '0';
      v_count := v_count + 1;

      IF v_count = c_baud_tick_period THEN
        baud_tick <= '1';
        v_count := 0;
      END IF;

      IF reset = '1' THEN
        v_count := 0;
      END IF;
    END IF;
  END PROCESS;

  p_filter : PROCESS (clk)
  BEGIN
    IF rising_edge(clk) THEN
      -- filtered output is majority out of 3
      rx_filter <= (rx_sr(0) AND rx_sr(1)) OR (rx_sr(1) AND rx_sr(2)) OR (rx_sr(0) AND rx_sr(2));

      IF baud_tick = '1' THEN
        rx_sr <= rx_sr(1 DOWNTO 0) & rx_sync;
      END IF;

      IF reset = '1' THEN
        rx_sr <= (OTHERS => '1');
      END IF;
    END IF;
  END PROCESS;

  p_align_samples : PROCESS (clk) BEGIN IF rising_edge(clk) THEN
    sample <= '0';
    IF baud_tick = '1' THEN
      IF state = Idle THEN
        sample_count <= 0;
      ELSIF state = Start THEN
        IF sample_count = 8 THEN
          sample <= '1';
          sample_count <= 0;
        ELSE
          sample_count <= sample_count + 1;
        END IF;
      ELSE
        IF sample_count = 15 THEN
          sample <= '1';
          sample_count <= 0;
        ELSE
          sample_count <= sample_count + 1;
        END IF;
      END IF;
    END IF;
    IF reset = '1' THEN
      sample_count <= 0;
    END IF;
  END IF;
END PROCESS;

p_state_machine : PROCESS (clk)
  VARIABLE v_count : INTEGER := 0;
BEGIN
  IF rising_edge(clk) THEN
    uart_error <= '0';
    m_axis_tvalid <= '0';

    CASE state IS
      WHEN Idle =>
        bit_index <= (OTHERS => '0');
        data_i <= (OTHERS => '0');
        IF rx_filter = '0' THEN
          state <= Start;
        END IF;
      WHEN Start =>
        IF sample = '1' THEN
          IF rx_filter = '0' THEN
            bit_index(bit_index'left) <= '1';
            state <= Data;
          ELSE
            state <= Idle;
          END IF;
        END IF;
      WHEN Data =>
        IF sample = '1' THEN
          bit_index <= STD_LOGIC_VECTOR(shift_right(unsigned(bit_index), 1));
          data_i <= rx_filter & data_i(data_i'left DOWNTO 1);

          IF bit_index(0) = '1' THEN
            state <= Stop;
          END IF;
        END IF;
      WHEN Stop =>
        IF sample = '1' THEN
          IF rx_filter = '1' THEN
            state <= Idle;
            m_axis_tdata <= data_i;
            m_axis_tvalid <= '1';
          ELSE
            state <= Error;
          END IF;
        END IF;
      WHEN Error =>
        state <= Idle;
        uart_error <= '1';
    END CASE;

    IF reset = '1' THEN
      state <= Idle;
    END IF;
  END IF;
END PROCESS;
END ARCHITECTURE;

interfaces/uart/build/waveform.vcd
$date
  Wed Mar 25 16:51:23 2026
$end
$version
  GHDL v0
$end
$timescale
  1 ps
$end
$scope module standard $end
$upscope $end
$scope module std_logic_1164 $end
$upscope $end
$scope module numeric_std $end
$upscope $end
$scope module math_real $end
$upscope $end
$scope module uart_rx $end
$var reg 1 ! clk $end
$var reg 1 " reset $end
$var reg 1 # rx $end
$var reg 8 $ m_axis_tdata[7:0] $end
$var reg 1 % m_axis_tvalid $end
$var reg 1 & uart_error $end
$var reg 1 ' baud_tick $end
$var reg 1 ( sample $end
$var integer 32 ) sample_count $end
$comment state is not handled $end
$var reg 1 * rx_sync $end
$var reg 3 + rx_sr[2:0] $end
$var reg 1 , rx_filter $end
$var reg 8 - data_i[7:0] $end
$var reg 8 . bit_index[7:0] $end
$scope module input_sync_inst $end
$var reg 1 / input $end
$var reg 1 0 reset $end
$var reg 1 1 dest_clk $end
$var reg 1 2 output $end
$var reg 2 3 output_sr[1:0] $end
$upscope $end
$upscope $end
$enddefinitions $end
#0
1!
1"
U#
bUUUUUUUU $
U%
U&
U'
U(
b0 )
1*
bUUU +
U,
bUUUUUUUU -
bUUUUUUUU .
U/
10
11
12
b11 3
#5000
0!
01
#10000
1!
0%
0&
0'
0(
b111 +
b00000000 -
b00000000 .
11
#15000
0!
01
#20000
1!
1,
11
#25000
0!
01
#30000
1!
11
#35000
0!
01
#40000
1!
11
#45000
0!
01
#50000
1!
11
#55000
0!
01
#60000
1!
11
#65000
0!
01
#70000
1!
11
#75000
0!
01
#80000
1!
11
#85000
0!
01
#90000
1!
11
#95000
0!
01
#100000
1!
11
#105000
0!
01
#110000
1!
11
#115000
0!
01
#120000
1!
11
#125000
0!
01
#130000
1!
11
#135000
0!
01
#140000
1!
11
#145000
0!
01
#150000
1!
11
#155000
0!
01
#160000
1!
11
#165000
0!
01
#170000
1!
11
#175000
0!
01
#180000
1!
11
#185000
0!
01
#190000
1!
11
#195000
0!
01
#200000
1!
11
#205000
0!
01
#210000
1!
11
#215000
0!
01
#220000
1!
11
#225000
0!
01
#230000
1!
11
#235000
0!
01
#240000
1!
11
#245000
0!
01
#250000
1!
11
#255000
0!
01
#260000
1!
11
#265000
0!
01
#270000
1!
11
#275000
0!
01
#280000
1!
11
#285000
0!
01
#290000
1!
11
#295000
0!
01
#300000
1!
11
#305000
0!
01
#310000
1!
11
#315000
0!
01
#320000
1!
11
#325000
0!
01
#330000
1!
11
#335000
0!
01
#340000
1!
11
#345000
0!
01
#350000
1!
11
#355000
0!
01
#360000
1!
11
#365000
0!
01
#370000
1!
11
#375000
0!
01
#380000
1!
11
#385000
0!
01
#390000
1!
11
#395000
0!
01
#400000
1!
11
#405000
0!
01
#410000
1!
11
#415000
0!
01
#420000
1!
11
#425000
0!
01
#430000
1!
11
#435000
0!
01
#440000
1!
11
#445000
0!
01
#450000
1!
11
#455000
0!
01
#460000
1!
11
#465000
0!
01
#470000
1!
11
#475000
0!
01
#480000
1!
11
#485000
0!
01
#490000
1!
11
#495000
0!
01
#500000
1!
11
#505000
0!
01
#510000
1!
11
#515000
0!
01
#520000
1!
11
#525000
0!
01
#530000
1!
11
#535000
0!
01
#540000
1!
11
#545000
0!
01
#550000
1!
11
#555000
0!
01
#560000
1!
11
#565000
0!
01
#570000
1!
11
#575000
0!
01
#580000
1!
11
#585000
0!
01
#590000
1!
11
#595000
0!
01
#600000
1!
11
#605000
0!
01
#610000
1!
11
#615000
0!
01
#620000
1!
11
#625000
0!
01
#630000
1!
11
#635000
0!
01
#640000
1!
11
#645000
0!
01
#650000
1!
11
#655000
0!
01
#660000
1!
11
#665000
0!
01
#670000
1!
11
#675000
0!
01
#680000
1!
11
#685000
0!
01
#690000
1!
11
#695000
0!
01
#700000
1!
11
#705000
0!
01
#710000
1!
11
#715000
0!
01
#720000
1!
11
#725000
0!
01
#730000
1!
11
#735000
0!
01
#740000
1!
11
#745000
0!
01
#750000
1!
11
#755000
0!
01
#760000
1!
11
#765000
0!
01
#770000
1!
11
#775000
0!
01
#780000
1!
11
#785000
0!
01
#790000
1!
11
#795000
0!
01
#800000
1!
11
#805000
0!
01
#810000
1!
11
#815000
0!
01
#820000
1!
11
#825000
0!
01
#830000
1!
11
#835000
0!
01
#840000
1!
11
#845000
0!
01
#850000
1!
11
#855000
0!
01
#860000
1!
11
#865000
0!
01
#870000
1!
11
#875000
0!
01
#880000
1!
11
#885000
0!
01
#890000
1!
11
#895000
0!
01
#900000
1!
11
#905000
0!
01
#910000
1!
11
#915000
0!
01
#920000
1!
11
#925000
0!
01
#930000
1!
11
#935000
0!
01
#940000
1!
11
#945000
0!
01
#950000
1!
11
#955000
0!
01
#960000
1!
11
#965000
0!
01
#970000
1!
11
#975000
0!
01
#980000
1!
11
#985000
0!
01
#990000
1!
0"
0#
0/
00
11
#995000
0!
01
#1000000
1!
11
b10 3
#1005000
0!
01
#1010000
1!
0*
11
02
b00 3
#1015000
0!
01
#1020000
1!
11
#1025000
0!
01
#1030000
1!
11
#1035000
0!
01
#1040000
1!
11
#1045000
0!
01
#1050000
1!
11
#1055000
0!
01
#1060000
1!
11
#1065000
0!
01
#1070000
1!
11
#1075000
0!
01
#1080000
1!
11
#1085000
0!
01
#1090000
1!
11
#1095000
0!
01
#1100000
1!
11
#1105000
0!
01
#1110000
1!
11
#1115000
0!
01
#1120000
1!
11
#1125000
0!
01
#1130000
1!
11
#1135000
0!
01
#1140000
1!
11
#1145000
0!
01
#1150000
1!
11
#1155000
0!
01
#1160000
1!
11
#1165000
0!
01
#1170000
1!
11
#1175000
0!
01
#1180000
1!
11
#1185000
0!
01
#1190000
1!
11
#1195000
0!
01
#1200000
1!
11
#1205000
0!
01
#1210000
1!
11
#1215000
0!
01
#1220000
1!
11
#1225000
0!
01
#1230000
1!
11
#1235000
0!
01
#1240000
1!
11
#1245000
0!
01
#1250000
1!
11
#1255000
0!
01
#1260000
1!
11
#1265000
0!
01
#1270000
1!
11
#1275000
0!
01
#1280000
1!
11
#1285000
0!
01
#1290000
1!
11
#1295000
0!
01
#1300000
1!
11
#1305000
0!
01
#1310000
1!
11
#1315000
0!
01
#1320000
1!
11
#1325000
0!
01
#1330000
1!
11
#1335000
0!
01
#1340000
1!
11
#1345000
0!
01
#1350000
1!
11
#1355000
0!
01
#1360000
1!
11
#1365000
0!
01
#1370000
1!
11
#1375000
0!
01
#1380000
1!
11
#1385000
0!
01
#1390000
1!
11
#1395000
0!
01
#1400000
1!
11
#1405000
0!
01
#1410000
1!
11
#1415000
0!
01
#1420000
1!
11
#1425000
0!
01
#1430000
1!
11
#1435000
0!
01
#1440000
1!
11
#1445000
0!
01
#1450000
1!
11
#1455000
0!
01
#1460000
1!
11
#1465000
0!
01
#1470000
1!
11
#1475000
0!
01
#1480000
1!
11
#1485000
0!
01
#1490000
1!
11
#1495000
0!
01
#1500000
1!
11
#1505000
0!
01
#1510000
1!
11
#1515000
0!
01
#1520000
1!
11
#1525000
0!
01
#1530000
1!
1'
11
#1535000
0!
01
#1540000
1!
0'
b110 +
11
