components/axis_fifo/vhdl_sources/axis_fifo.vhd
LIBRARY ieee;
USE ieee.std_logic_1164.ALL;
USE ieee.numeric_std.ALL;
USE ieee.math_real.ALL;

ENTITY axis_fifo IS
  GENERIC (
    g_word_depth : INTEGER := 16; -- power of 2
    g_tdata_width : INTEGER := 32;
    g_tuser_width : INTEGER := 8
  );
  PORT (
    clk : IN STD_LOGIC;
    reset : IN STD_LOGIC;

    s_axis_tvalid : IN STD_LOGIC;
    s_axis_tready : OUT STD_LOGIC;
    s_axis_tlast : IN STD_LOGIC;
    s_axis_tdata : IN STD_LOGIC_VECTOR(g_tdata_width - 1 DOWNTO 0);
    s_axis_tuser : IN STD_LOGIC_VECTOR(g_tuser_width - 1 DOWNTO 0);

    m_axis_tvalid : OUT STD_LOGIC;
    m_axis_tready : IN STD_LOGIC;
    m_axis_tlast : OUT STD_LOGIC;
    m_axis_tdata : OUT STD_LOGIC_VECTOR(g_tdata_width - 1 DOWNTO 0);
    m_axis_tuser : OUT STD_LOGIC_VECTOR(g_tuser_width - 1 DOWNTO 0)

  );
END ENTITY;

ARCHITECTURE behavior OF axis_fifo IS
  TYPE t_ram_tdata IS ARRAY (0 TO g_word_depth - 1) OF STD_LOGIC_VECTOR(s_axis_tdata'RANGE);
  TYPE t_ram_tuser IS ARRAY (0 TO g_word_depth - 1) OF STD_LOGIC_VECTOR(s_axis_tuser'RANGE);
  TYPE t_ram_tlast IS ARRAY (0 TO g_word_depth - 1) OF STD_LOGIC;
  SIGNAL ram_tdata : t_ram_tdata;
  SIGNAL ram_tuser : t_ram_tuser;
  SIGNAL ram_tlast : t_ram_tlast;

  SIGNAL read_pointer : UNSIGNED(INTEGER(log2(real(g_word_depth))) - 1 DOWNTO 0);
  SIGNAL write_pointer : UNSIGNED(INTEGER(log2(real(g_word_depth))) - 1 DOWNTO 0);

  SIGNAL s_tready : STD_LOGIC := '1';

  SIGNAL full : STD_LOGIC;
  SIGNAL empty : STD_LOGIC;
BEGIN
  s_tready <= NOT full;
  s_axis_tready <= s_tready;

  p_full_gen : PROCESS (write_pointer, read_pointer, reset)
  BEGIN
    full <= '0';
    IF write_pointer + 1 = read_pointer THEN
      full <= '1';
    END IF;

    IF reset = '1' THEN
      full <= '0';
    END IF;
  END PROCESS;

  p_empty_gen : PROCESS (write_pointer, read_pointer, reset)
  BEGIN
    empty <= '0';
    IF write_pointer = read_pointer THEN
      empty <= '1';
    END IF;

    IF reset = '1' THEN
      empty <= '1';
    END IF;
  END PROCESS;

  p_write : PROCESS (clk)
  BEGIN
    IF rising_edge(clk) THEN
      IF s_axis_tvalid = '1' AND s_tready = '1' THEN
        ram_tdata(to_integer(write_pointer)) <= s_axis_tdata;
        ram_tuser(to_integer(write_pointer)) <= s_axis_tuser;
        ram_tlast(to_integer(write_pointer)) <= s_axis_tlast;

        write_pointer <= write_pointer + 1;
      END IF;

      IF reset = '1' THEN
        write_pointer <= (OTHERS => '0');
      END IF;
    END IF;
  END PROCESS;

  p_read : PROCESS (clk)
  BEGIN
    IF rising_edge(clk) THEN
      m_axis_tvalid <= NOT empty;
      m_axis_tdata <= ram_tdata(to_integer(read_pointer));
      m_axis_tuser <= ram_tuser(to_integer(read_pointer));
      m_axis_tlast <= ram_tlast(to_integer(read_pointer));

      IF m_axis_tready = '1' AND empty = '0' THEN
        read_pointer <= read_pointer + 1;
      END IF;
      IF reset = '1' THEN
        m_axis_tvalid <= '0';
        read_pointer <= (OTHERS => '0');
      END IF;
    END IF;
  END PROCESS;

END ARCHITECTURE behavior;

components/axis_fifo/build/waveform.vcd
$date
  Wed Mar 25 18:36:14 2026
$end
$version
  GHDL v0
$end
$timescale
  1 ps
$end
$scope module standard $end
$upscope $end
$scope module std_logic_1164 $end
$upscope $end
$scope module numeric_std $end
$upscope $end
$scope module math_real $end
$upscope $end
$scope module axis_fifo $end
$var reg 1 ! clk $end
$var reg 1 " reset $end
$var reg 1 # s_axis_tvalid $end
$var reg 1 $ s_axis_tready $end
$var reg 1 % s_axis_tlast $end
$var reg 32 & s_axis_tdata[31:0] $end
$var reg 8 ' s_axis_tuser[7:0] $end
$var reg 1 ( m_axis_tvalid $end
$var reg 1 ) m_axis_tready $end
$var reg 1 * m_axis_tlast $end
$var reg 32 + m_axis_tdata[31:0] $end
$var reg 8 , m_axis_tuser[7:0] $end
$comment ram_tdata is not handled $end
$comment ram_tuser is not handled $end
$var reg 16 - ram_tlast[0:15] $end
$var reg 4 . read_pointer[3:0] $end
$var reg 4 / write_pointer[3:0] $end
$var reg 1 0 s_tready $end
$var reg 1 1 full $end
$var reg 1 2 empty $end
$upscope $end
$enddefinitions $end
#0
1!
1"
U#
1$
U%
bUUUUUUUUUUUUUUUUUUUUUUUUUUUUUUUU &
bUUUUUUUU '
U(
U)
U*
bUUUUUUUUUUUUUUUUUUUUUUUUUUUUUUUU +
bUUUUUUUU ,
bUUUUUUUUUUUUUUUU -
bUUUU .
bUUUU /
10
01
12
#5000
0!
#10000
1!
0(
b0000 .
b0000 /
#15000
0!
#20000
1!
#25000
0!
#30000
1!
#35000
0!
#40000
1!
#45000
0!
#50000
1!
#55000
0!
#60000
1!
#65000
0!
#70000
1!
#75000
0!
#80000
1!
#85000
0!
#90000
1!
#95000
0!
#100000
1!
#105000
0!
#110000
1!
#115000
0!
#120000
1!
#125000
0!
#130000
1!
#135000
0!
#140000
1!
#145000
0!
#150000
1!
#155000
0!
#160000
1!
#165000
0!
#170000
1!
#175000
0!
#180000
1!
#185000
0!
#190000
1!
#195000
0!
#200000
1!
#205000
0!
#210000
1!
#215000
0!
#220000
1!
#225000
0!
#230000
1!
#235000
0!
#240000
1!
#245000
0!
#250000
1!
#255000
0!
#260000
1!
#265000
0!
#270000
1!
#275000
0!
#280000
1!
#285000
0!
#290000
1!
#295000
0!
#300000
1!
#305000
0!
#310000
1!
#315000
0!
#320000
1!
#325000
0!
#330000
1!
#335000
0!
#340000
1!
#345000
0!
#350000
1!
#355000
0!
#360000
1!
#365000
0!
#370000
1!
#375000
0!
#380000
1!
#385000
0!
#390000
1!
#395000
0!
#400000
1!
#405000
0!
#410000
1!
#415000
0!
#420000
1!
#425000
0!
#430000
1!
#435000
0!
#440000
1!
#445000
0!
#450000
1!
#455000
0!
#460000
1!
#465000
0!
#470000
1!
#475000
0!
#480000
1!
#485000
0!
#490000
1!
#495000
0!
#500000
1!
#505000
0!
#510000
1!
#515000
0!
#520000
1!
#525000
0!
#530000
1!
#535000
0!
#540000
1!
#545000
0!
#550000
1!
#555000
0!
#560000
1!
#565000
0!
#570000
1!
#575000
0!
#580000
1!
#585000
0!
#590000
1!
#595000
0!
#600000
1!
#605000
0!
#610000
1!
#615000
0!
#620000
1!
#625000
0!
#630000
1!
#635000
0!
#640000
1!
#645000
0!
#650000
1!
#655000
0!
#660000
1!
#665000
0!
#670000
1!
#675000
0!
#680000
1!
#685000
0!
#690000
1!
#695000
0!
#700000
1!
#705000
0!
#710000
1!
#715000
0!
#720000
1!
#725000
0!
#730000
1!
#735000
0!
#740000
1!
#745000
0!
#750000
1!
#755000
0!
#760000
1!
#765000
0!
#770000
1!
#775000
0!
#780000
1!
#785000
0!
#790000
1!
#795000
0!
#800000
1!
#805000
0!
#810000
1!
#815000
0!
#820000
1!
#825000
0!
#830000
1!
#835000
0!
#840000
1!
#845000
0!
#850000
1!
#855000
0!
#860000
1!
#865000
0!
#870000
1!
#875000
0!
#880000
1!
#885000
0!
#890000
1!
#895000
0!
#900000
1!
#905000
0!
#910000
1!
#915000
0!
#920000
1!
#925000
0!
#930000
1!
#935000
0!
#940000
1!
#945000
0!
#950000
1!
#955000
0!
#960000
1!
#965000
0!
#970000
1!
#975000
0!
#980000
1!
#985000
0!
#990000
1!
0"
0#
X%
bXXXXXXXXXXXXXXXXXXXXXXXXXXXXXXXX &
bXXXXXXXX '
0)
#995000
0!
#1000000
1!
1#
0%
b00000011000000100000000100000000 &
b00000000 '
1)
#1005000
0!
#1010000
1!
b00000111000001100000010100000100 &
b0UUUUUUUUUUUUUUU -
b0001 /
02
#1015000
0!
#1020000
1!
b00001011000010100000100100001000 &
1(
0*
b00000011000000100000000100000000 +
b00000000 ,
b00UUUUUUUUUUUUUU -
b0001 .
b0010 /
#1025000
0!
#1030000
1!
b00001111000011100000110100001100 &
b00000111000001100000010100000100 +
b000UUUUUUUUUUUUU -
b0010 .
b0011 /
#1035000
0!
#1040000
1!
b00010011000100100001000100010000 &
b00001011000010100000100100001000 +
b0000UUUUUUUUUUUU -
b0011 .
b0100 /
#1045000
0!
#1050000
1!
b00010111000101100001010100010100 &
b00001111000011100000110100001100 +
b00000UUUUUUUUUUU -
b0100 .
b0101 /
#1055000
0!
#1060000
1!
b00011011000110100001100100011000 &
b00010011000100100001000100010000 +
b000000UUUUUUUUUU -
b0101 .
b0110 /
#1065000
0!
#1070000
1!
1%
b00011111000111100001110100011100 &
b00010111000101100001010100010100 +
b0000000UUUUUUUUU -
b0110 .
b0111 /
#1075000
0!
#1080000
1!
0#
0%
b00011011000110100001100100011000 +
b00000001UUUUUUUU -
b0111 .
b1000 /
#1085000
0!
#1090000
1!
1*
b00011111000111100001110100011100 +
b1000 .
12
#1095000
0!
#1100000
1!
0(
U*
bUUUUUUUUUUUUUUUUUUUUUUUUUUUUUUUU +
bUUUUUUUU ,
